mlrun_pipelines/client.py
mlrun_pipelines/helpers.py
mlrun_pipelines/imports.py
mlrun_pipelines/mixins.py
mlrun_pipelines/models.py
mlrun_pipelines/mounts.py
mlrun_pipelines/ops.py
mlrun_pipelines/patcher.py
mlrun_pipelines/utils.py
mlrun_pipelines_kfp_v1_8-0.5.9.dist-info/METADATA
mlrun_pipelines_kfp_v1_8-0.5.9.dist-info/WHEEL
mlrun_pipelines_kfp_v1_8-0.5.9.dist-info/top_level.txt
mlrun_pipelines_kfp_v1_8-0.5.9.dist-info/RECORD
