Metadata-Version: 2.4
Name: mlrun-pipelines-kfp-v1-8
Version: 0.5.9
Summary: MLRun Pipelines adapter package for providing KFP 1.8 compatibility
Author-email: Yaron Haviv <yaronh@iguazio.com>
License: Apache License 2.0
Project-URL: homepage, https://github.com/mlrun/mlrun
Keywords: mlrun,kfp
Requires-Python: <3.12,>=3.9
Requires-Dist: inflection>=0.5.1
Requires-Dist: kfp_server_api~=1.8
Provides-Extra: kfp
Requires-Dist: kfp~=1.8.22; python_version < "3.11" and extra == "kfp"
Requires-Dist: kfp~=1.8.23; python_version >= "3.11" and extra == "kfp"
